pyrayt/__init__.py
pyrayt/_pyrayt.py
pyrayt/components.py
pyrayt/materials.py
pyrayt/utils.py
tinygfx/__init__.py
tinygfx/g3d/__init__.py
tinygfx/g3d/csg.py
tinygfx/g3d/materials/__init__.py
tinygfx/g3d/materials/color.py
tinygfx/g3d/materials/gooch.py
tinygfx/g3d/operations.py
tinygfx/g3d/primitives.py
tinygfx/g3d/renderers.py
tinygfx/g3d/world_objects.py
pyrayt-0.3.1.dist-info/LICENSE.txt
pyrayt-0.3.1.dist-info/WHEEL
pyrayt-0.3.1.dist-info/METADATA
pyrayt-0.3.1.dist-info/RECORD
