Metadata-Version: 2.1
Name: pyrayt
Version: 0.3.1
Summary: a toolchain for developing and simulating optical packages
License: MIT
Author: Frazier, Ryan
Requires-Python: >=3.7.0,<3.9
Classifier: License :: OSI Approved :: MIT License
Classifier: Programming Language :: Python :: 3
Classifier: Programming Language :: Python :: 3.7
Classifier: Programming Language :: Python :: 3.8
Requires-Dist: matplotlib (>=3.3.4,<4.0.0)
Requires-Dist: numpy (>=1.20.0,<2.0.0)
Requires-Dist: pandas (>=1.2.2,<2.0.0)
Requires-Dist: scipy (>=1.6.0,<2.0.0)
